ahds/__init__.py
ahds/ahds.py
ahds/core.py
ahds/data_stream.py
ahds/decoders.cpython-39-darwin.so
ahds/extra.py
ahds/grammar.py
ahds/header.py
ahds/proc.py
ahds/tests/__init__.py
ahds/tests/test_ahds.py
ahds/tests/test_core.py
ahds/tests/test_data_streams.py
ahds/tests/test_extra.py
ahds/tests/test_grammar.py
ahds/tests/test_header.py
ahds-0.2.4.dist-info/LICENSE
ahds-0.2.4.dist-info/METADATA
ahds-0.2.4.dist-info/WHEEL
ahds-0.2.4.dist-info/entry_points.txt
ahds-0.2.4.dist-info/top_level.txt
ahds-0.2.4.dist-info/RECORD
