Metadata-Version: 2.1
Name: ahds
Version: 0.2.4
Summary: Python package to parse and provide access to headers and data streams in Amira (R) files
Home-page: https://github.com/emdb-empiar/ahds.git
Author: Paul K. Korir, PhD
Author-email: pkorir@ebi.ac.uk, paul.korir@gmail.com
License: Apache License
Keywords: header,parser,data streams
Platform: UNKNOWN
Classifier: Development Status :: 2 - Pre-Alpha
Classifier: Environment :: Console
Classifier: Intended Audience :: Developers
Classifier: License :: OSI Approved :: Apache Software License
Classifier: Operating System :: OS Independent
Classifier: Programming Language :: Python :: 2
Classifier: Programming Language :: Python :: 2.7
Classifier: Programming Language :: Python :: 3
Classifier: Programming Language :: Python :: 3.5
Classifier: Programming Language :: Python :: 3.6
Classifier: Programming Language :: Python :: 3.7
Classifier: Topic :: Software Development :: Libraries :: Python Modules
Classifier: Topic :: Terminals
Classifier: Topic :: Text Processing
Classifier: Topic :: Text Processing :: Markup
Classifier: Topic :: Utilities
License-File: LICENSE
Requires-Dist: simpleparse
Requires-Dist: scikit-image
